{
    "id": "526225",
    "ident": "02NM",
    "type": "small_airport",
    "name": "FFR Animas Landing Strip",
    "latitude_deg": "32.09071",
    "longitude_deg": "-108.870735",
    "elevation_ft": "4240",
    "continent": "NA",
    "iso_country": "US",
    "iso_region": "US-NM",
    "municipality": "Animas",
    "scheduled_service": "no",
    "gps_code": "02NM",
    "iata_code": "",
    "local_code": "02NM",
    "home_link": "",
    "wikipedia_link": "",
    "keywords": "",
    "runways": [
        {
            "id": "526226",
            "airport_ref": "526225",
            "airport_ident": "02NM",
            "length_ft": "4247",
            "width_ft": "30",
            "surface": "Dirt",
            "lighted": "0",
            "closed": "0",
            "le_ident": "8",
            "le_latitude_deg": "",
            "le_longitude_deg": "",
            "le_elevation_ft": "",
            "le_heading_degT": "",
            "le_displaced_threshold_ft": "",
            "he_ident": "26",
            "he_latitude_deg": "",
            "he_longitude_deg": "",
            "he_elevation_ft": "",
            "he_heading_degT": "",
            "he_displaced_threshold_ft": ""
        }
    ],
    "country": {
        "id": "302755",
        "code": "US",
        "name": "United States",
        "continent": "NA",
        "wikipedia_link": "https://en.wikipedia.org/wiki/United_States",
        "keywords": "American airports"
    },
    "region": {
        "id": "306108",
        "code": "US-NM",
        "local_code": "NM",
        "name": "New Mexico",
        "continent": "NA",
        "iso_country": "US",
        "wikipedia_link": "https://en.wikipedia.org/wiki/New_Mexico",
        "keywords": "Airports in New Mexico"
    }
}