{
    "id": "602643",
    "ident": "BR-3280",
    "type": "small_airport",
    "name": "Capanema Airstrip",
    "latitude_deg": "-10.621778",
    "longitude_deg": "-45.386297",
    "elevation_ft": "2539",
    "continent": "SA",
    "iso_country": "BR",
    "iso_region": "BR-PI",
    "municipality": "Corrente",
    "scheduled_service": "no",
    "icao_code": "",
    "iata_code": "",
    "gps_code": "SD54",
    "local_code": "PI0125",
    "home_link": "",
    "wikipedia_link": "",
    "keywords": "",
    "runways": [
        {
            "id": "602644",
            "airport_ref": "602643",
            "airport_ident": "BR-3280",
            "length_ft": "3495",
            "width_ft": "66",
            "surface": "GVL",
            "lighted": "0",
            "closed": "0",
            "le_ident": "01",
            "le_latitude_deg": "",
            "le_longitude_deg": "",
            "le_elevation_ft": "",
            "le_heading_degT": "",
            "le_displaced_threshold_ft": "",
            "he_ident": "19",
            "he_latitude_deg": "",
            "he_longitude_deg": "",
            "he_elevation_ft": "",
            "he_heading_degT": "",
            "he_displaced_threshold_ft": ""
        }
    ],
    "country": {
        "id": "302791",
        "code": "BR",
        "name": "Brazil",
        "continent": "SA",
        "wikipedia_link": "https://en.wikipedia.org/wiki/Brazil",
        "keywords": "Brasil, Brasilian, Aeroportos do Brasil"
    },
    "region": {
        "id": "303215",
        "code": "BR-PI",
        "local_code": "PI",
        "name": "Piauí",
        "continent": "SA",
        "iso_country": "BR",
        "wikipedia_link": "https://en.wikipedia.org/wiki/Piauí",
        "keywords": "Airports in Piauí"
    }
}