{
    "id": "515458",
    "ident": "CZ-0222",
    "type": "heliport",
    "name": "Hranice Hospital Heliport",
    "latitude_deg": "49.55564",
    "longitude_deg": "17.74896",
    "elevation_ft": "912",
    "continent": "EU",
    "iso_country": "CZ",
    "iso_region": "CZ-OL",
    "municipality": "Hranice",
    "scheduled_service": "no",
    "icao_code": "",
    "iata_code": "",
    "gps_code": "",
    "local_code": "",
    "home_link": "",
    "wikipedia_link": "",
    "keywords": "",
    "country": {
        "id": "302680",
        "code": "CZ",
        "name": "Czech Republic",
        "continent": "EU",
        "wikipedia_link": "https://en.wikipedia.org/wiki/Czech_Republic",
        "keywords": "Letiště České republiky, Czechia"
    },
    "region": {
        "id": "303538",
        "code": "CZ-OL",
        "local_code": "OL",
        "name": "Olomouc Region",
        "continent": "EU",
        "iso_country": "CZ",
        "wikipedia_link": "https://en.wikipedia.org/wiki/Olomouc_Region",
        "keywords": "Olomoucký kraj, Moravia"
    }
}