{
    "id": "316140",
    "ident": "DE-0344",
    "type": "small_airport",
    "name": "Göpfersdorf Airfield",
    "latitude_deg": "50.913871",
    "longitude_deg": "12.612927",
    "elevation_ft": "960",
    "continent": "EU",
    "iso_country": "DE",
    "iso_region": "DE-TH",
    "municipality": "Göpfersdorf",
    "scheduled_service": "no",
    "gps_code": "",
    "iata_code": "",
    "local_code": "",
    "home_link": "http://www.flugsportverein-altenburger-land.de/",
    "wikipedia_link": "",
    "keywords": "Flugplatz Göpfersdorf",
    "country": {
        "id": "302681",
        "code": "DE",
        "name": "Germany",
        "continent": "EU",
        "wikipedia_link": "https://en.wikipedia.org/wiki/Germany",
        "keywords": "Flughäfen in Deutschland"
    },
    "region": {
        "id": "303562",
        "code": "DE-TH",
        "local_code": "TH",
        "name": "Thuringia",
        "continent": "EU",
        "iso_country": "DE",
        "wikipedia_link": "https://en.wikipedia.org/wiki/Thuringia",
        "keywords": "Thueringen, Freistaat Thüringen"
    }
}