{
    "id": "29236",
    "ident": "EKHG",
    "type": "small_airport",
    "name": "Herning Airfield",
    "latitude_deg": "56.1847",
    "longitude_deg": "9.04445",
    "elevation_ft": "167",
    "continent": "EU",
    "iso_country": "DK",
    "iso_region": "DK-82",
    "municipality": "Herning",
    "scheduled_service": "no",
    "icao_code": "",
    "iata_code": "",
    "gps_code": "EKHG",
    "local_code": "",
    "home_link": "http://www.ekhg.dk/?lang=en",
    "wikipedia_link": "https://en.wikipedia.org/wiki/Herning_Airport",
    "keywords": "",
    "runways": [
        {
            "id": "259851",
            "airport_ref": "29236",
            "airport_ident": "EKHG",
            "length_ft": "3934",
            "width_ft": "98",
            "surface": "Asphalt",
            "lighted": "0",
            "closed": "0",
            "le_ident": "09",
            "le_latitude_deg": "56.185081",
            "le_longitude_deg": "9.031193",
            "le_elevation_ft": "167",
            "le_heading_degT": "",
            "le_displaced_threshold_ft": "",
            "he_ident": "27",
            "he_latitude_deg": "56.18459",
            "he_longitude_deg": "9.050468",
            "he_elevation_ft": "167",
            "he_heading_degT": "",
            "he_displaced_threshold_ft": ""
        },
        {
            "id": "553371",
            "airport_ref": "29236",
            "airport_ident": "EKHG",
            "length_ft": "2854",
            "width_ft": "98",
            "surface": "Grass",
            "lighted": "0",
            "closed": "0",
            "le_ident": "09GL",
            "le_latitude_deg": "56.18622",
            "le_longitude_deg": "9.034522",
            "le_elevation_ft": "167",
            "le_heading_degT": "",
            "le_displaced_threshold_ft": "",
            "he_ident": "27GL",
            "he_latitude_deg": "56.18595",
            "he_longitude_deg": "9.048507",
            "he_elevation_ft": "167",
            "he_heading_degT": "",
            "he_displaced_threshold_ft": ""
        },
        {
            "id": "553372",
            "airport_ref": "29236",
            "airport_ident": "EKHG",
            "length_ft": "2188",
            "width_ft": "98",
            "surface": "Grass",
            "lighted": "0",
            "closed": "0",
            "le_ident": "15",
            "le_latitude_deg": "56.18785",
            "le_longitude_deg": "9.041596",
            "le_elevation_ft": "167",
            "le_heading_degT": "",
            "le_displaced_threshold_ft": "410",
            "he_ident": "33",
            "he_latitude_deg": "56.182306",
            "he_longitude_deg": "9.046713",
            "he_elevation_ft": "167",
            "he_heading_degT": "",
            "he_displaced_threshold_ft": "410"
        }
    ],
    "freqs": [
        {
            "id": "75396",
            "airport_ref": "29236",
            "airport_ident": "EKHG",
            "type": "RADIO",
            "description": "Herning Radio",
            "frequency_mhz": "121"
        }
    ],
    "country": {
        "id": "302682",
        "code": "DK",
        "name": "Denmark",
        "continent": "EU",
        "wikipedia_link": "https://en.wikipedia.org/wiki/Denmark",
        "keywords": "Lufthavnene i Danmark"
    },
    "region": {
        "id": "306328",
        "code": "DK-82",
        "local_code": "82",
        "name": "Central Jutland",
        "continent": "EU",
        "iso_country": "DK",
        "wikipedia_link": "https://en.wikipedia.org/wiki/Central_Denmark_Region",
        "keywords": "Central Denmark, Mid-Jutland, Midtjylland"
    }
}