{
    "id": "29325",
    "ident": "ESGH",
    "type": "small_airport",
    "name": "Herrljunga Airfield",
    "latitude_deg": "58.029301",
    "longitude_deg": "13.1082",
    "elevation_ft": "",
    "continent": "EU",
    "iso_country": "SE",
    "iso_region": "SE-Q",
    "municipality": "Herrljunga",
    "scheduled_service": "no",
    "icao_code": "",
    "iata_code": "",
    "gps_code": "ESGH",
    "local_code": "",
    "home_link": "",
    "wikipedia_link": "",
    "keywords": "",
    "freqs": [
        {
            "id": "332892",
            "airport_ref": "29325",
            "airport_ident": "ESGH",
            "type": "CTAF",
            "description": "HERRLJUNGA RADIO",
            "frequency_mhz": "123.65"
        }
    ],
    "country": {
        "id": "302715",
        "code": "SE",
        "name": "Sweden",
        "continent": "EU",
        "wikipedia_link": "https://en.wikipedia.org/wiki/Sweden",
        "keywords": "Flygplatserna, Sverige"
    },
    "region": {
        "id": "305424",
        "code": "SE-Q",
        "local_code": "Q",
        "name": "Västra Götalands län",
        "continent": "EU",
        "iso_country": "SE",
        "wikipedia_link": "https://en.wikipedia.org/wiki/Västra_Götalands_län",
        "keywords": "Västra Götaland County"
    }
}