{
    "id": "2773",
    "ident": "FABM",
    "type": "small_airport",
    "name": "Bethlehem Airport",
    "latitude_deg": "-28.2484",
    "longitude_deg": "28.3361",
    "elevation_ft": "5561",
    "continent": "AF",
    "iso_country": "ZA",
    "iso_region": "ZA-FS",
    "municipality": "Bethlehem",
    "scheduled_service": "no",
    "icao_code": "",
    "iata_code": "",
    "gps_code": "FABM",
    "local_code": "",
    "home_link": "",
    "wikipedia_link": "https://en.wikipedia.org/wiki/Bethlehem_Airport",
    "keywords": "",
    "runways": [
        {
            "id": "238790",
            "airport_ref": "2773",
            "airport_ident": "FABM",
            "length_ft": "3855",
            "width_ft": "49",
            "surface": "ASP",
            "lighted": "1",
            "closed": "0",
            "le_ident": "11",
            "le_latitude_deg": "-28.247800827026367",
            "le_longitude_deg": "28.33009910583496",
            "le_elevation_ft": "5517",
            "le_heading_degT": "96",
            "le_displaced_threshold_ft": "",
            "he_ident": "29",
            "he_latitude_deg": "-28.249000549316406",
            "he_longitude_deg": "28.342199325561523",
            "he_elevation_ft": "5561",
            "he_heading_degT": "276",
            "he_displaced_threshold_ft": ""
        },
        {
            "id": "238791",
            "airport_ref": "2773",
            "airport_ident": "FABM",
            "length_ft": "4301",
            "width_ft": "150",
            "surface": "GRS",
            "lighted": "0",
            "closed": "0",
            "le_ident": "13",
            "le_latitude_deg": "-28.244800567626953",
            "le_longitude_deg": "28.329099655151367",
            "le_elevation_ft": "5498",
            "le_heading_degT": "108",
            "le_displaced_threshold_ft": "",
            "he_ident": "31",
            "he_latitude_deg": "-28.24850082397461",
            "he_longitude_deg": "28.34160041809082",
            "he_elevation_ft": "5558",
            "he_heading_degT": "288",
            "he_displaced_threshold_ft": ""
        }
    ],
    "freqs": [
        {
            "id": "57092",
            "airport_ref": "2773",
            "airport_ident": "FABM",
            "type": "CTAF",
            "description": "CTAF",
            "frequency_mhz": "124.8"
        }
    ],
    "country": {
        "id": "302610",
        "code": "ZA",
        "name": "South Africa",
        "continent": "AF",
        "wikipedia_link": "https://en.wikipedia.org/wiki/South_Africa",
        "keywords": "South African airports"
    },
    "region": {
        "id": "306296",
        "code": "ZA-FS",
        "local_code": "FS",
        "name": "Free State",
        "continent": "AF",
        "iso_country": "ZA",
        "wikipedia_link": "https://en.wikipedia.org/wiki/Free_State_(province)",
        "keywords": "Airports in Free State"
    },
    "navaids": [
        {
            "id": "86174",
            "filename": "Bethlehem_NDB_ZA",
            "ident": "BM",
            "name": "Bethlehem",
            "type": "NDB",
            "frequency_khz": "343",
            "latitude_deg": "-28.249799728393555",
            "longitude_deg": "28.333599090576172",
            "elevation_ft": "",
            "iso_country": "ZA",
            "dme_frequency_khz": "",
            "dme_channel": "",
            "dme_latitude_deg": "",
            "dme_longitude_deg": "",
            "dme_elevation_ft": "",
            "slaved_variation_deg": "",
            "magnetic_variation_deg": "-20.42",
            "usageType": "BOTH",
            "power": "MEDIUM",
            "associated_airport": "FABM"
        }
    ]
}