{
    "id": "313926",
    "ident": "FBLO",
    "type": "small_airport",
    "name": "Lobatse Airport",
    "latitude_deg": "-25.1981",
    "longitude_deg": "25.7139",
    "elevation_ft": "3823",
    "continent": "AF",
    "iso_country": "BW",
    "iso_region": "BW-LO",
    "municipality": "Lobatse",
    "scheduled_service": "no",
    "icao_code": "FBLO",
    "iata_code": "LOQ",
    "gps_code": "FBLO",
    "local_code": "",
    "home_link": "",
    "wikipedia_link": "https://en.wikipedia.org/wiki/Lobatse_Airport",
    "keywords": "",
    "country": {
        "id": "302560",
        "code": "BW",
        "name": "Botswana",
        "continent": "AF",
        "wikipedia_link": "https://en.wikipedia.org/wiki/Botswana",
        "keywords": "Botswana airports"
    },
    "region": {
        "id": "353987",
        "code": "BW-LO",
        "local_code": "LO",
        "name": "Lobatse (town)",
        "continent": "AF",
        "iso_country": "BW",
        "wikipedia_link": "https://en.wikipedia.org/wiki/Lobatse",
        "keywords": "Airports in Lobatse (town)"
    }
}