{
    "id": "349443",
    "ident": "GR-0052",
    "type": "closed",
    "name": "Litochoro Airport",
    "latitude_deg": "40.12212",
    "longitude_deg": "22.53513",
    "elevation_ft": "338",
    "continent": "EU",
    "iso_country": "GR",
    "iso_region": "GR-B",
    "municipality": "Litochoro",
    "scheduled_service": "no",
    "icao_code": "",
    "iata_code": "",
    "gps_code": "",
    "local_code": "",
    "home_link": "",
    "wikipedia_link": "",
    "keywords": "",
    "country": {
        "id": "302691",
        "code": "GR",
        "name": "Greece",
        "continent": "EU",
        "wikipedia_link": "https://en.wikipedia.org/wiki/Greece",
        "keywords": "αεροδρόμια στην Ελλάδα"
    },
    "region": {
        "id": "430179",
        "code": "GR-B",
        "local_code": "B",
        "name": "Central Macedonia",
        "continent": "EU",
        "iso_country": "GR",
        "wikipedia_link": "https://en.wikipedia.org/wiki/Central_Macedonia",
        "keywords": "Κεντρική Μακεδονία"
    }
}