{
    "id": "347852",
    "ident": "GY-0005",
    "type": "small_airport",
    "name": "Kako Mountain Airstrip",
    "latitude_deg": "4.628142",
    "longitude_deg": "-60.056977",
    "elevation_ft": "1738",
    "continent": "SA",
    "iso_country": "GY",
    "iso_region": "GY-PT",
    "municipality": "Kako Mountain",
    "scheduled_service": "no",
    "icao_code": "",
    "iata_code": "",
    "gps_code": "",
    "local_code": "",
    "home_link": "",
    "wikipedia_link": "",
    "keywords": "",
    "country": {
        "id": "302797",
        "code": "GY",
        "name": "Guyana",
        "continent": "SA",
        "wikipedia_link": "https://en.wikipedia.org/wiki/Guyana",
        "keywords": "Guyanese airports"
    },
    "region": {
        "id": "304001",
        "code": "GY-PT",
        "local_code": "PT",
        "name": "Potaro-Siparuni",
        "continent": "SA",
        "iso_country": "GY",
        "wikipedia_link": "https://en.wikipedia.org/wiki/Potaro-Siparuni",
        "keywords": "Airports in Potaro-Siparuni"
    }
}