{
    "id": "3209",
    "ident": "HKKT",
    "type": "medium_airport",
    "name": "Kitale Airport",
    "latitude_deg": "0.971989",
    "longitude_deg": "34.958599",
    "elevation_ft": "6070",
    "continent": "AF",
    "iso_country": "KE",
    "iso_region": "KE-700",
    "municipality": "Kitale",
    "scheduled_service": "no",
    "icao_code": "HKKT",
    "iata_code": "KTL",
    "gps_code": "HKKT",
    "local_code": "",
    "home_link": "",
    "wikipedia_link": "https://en.wikipedia.org/wiki/Kitale_Airport",
    "keywords": "",
    "runways": [
        {
            "id": "237275",
            "airport_ref": "3209",
            "airport_ident": "HKKT",
            "length_ft": "4757",
            "width_ft": "75",
            "surface": "ASP",
            "lighted": "0",
            "closed": "0",
            "le_ident": "04",
            "le_latitude_deg": "0.9669110178947449",
            "le_longitude_deg": "34.95439910888672",
            "le_elevation_ft": "",
            "le_heading_degT": "40",
            "le_displaced_threshold_ft": "",
            "he_ident": "22",
            "he_latitude_deg": "0.9770640134811401",
            "he_longitude_deg": "34.96269989013672",
            "he_elevation_ft": "",
            "he_heading_degT": "220",
            "he_displaced_threshold_ft": ""
        }
    ],
    "country": {
        "id": "302579",
        "code": "KE",
        "name": "Kenya",
        "continent": "AF",
        "wikipedia_link": "https://en.wikipedia.org/wiki/Kenya",
        "keywords": "Kenyan airports"
    },
    "region": {
        "id": "304340",
        "code": "KE-700",
        "local_code": "700",
        "name": "Rift Valley Province",
        "continent": "AF",
        "iso_country": "KE",
        "wikipedia_link": "https://en.wikipedia.org/wiki/Rift_Valley_Province",
        "keywords": "Airports in Rift Valley Province"
    }
}