{
    "id": "529382",
    "ident": "LKJE",
    "type": "heliport",
    "name": "Jesenik Heliport",
    "latitude_deg": "50.221667",
    "longitude_deg": "17.186667",
    "elevation_ft": "1511",
    "continent": "EU",
    "iso_country": "CZ",
    "iso_region": "CZ-OL",
    "municipality": "",
    "scheduled_service": "no",
    "gps_code": "LKJE",
    "iata_code": "",
    "local_code": "",
    "home_link": "",
    "wikipedia_link": "",
    "keywords": "",
    "country": {
        "id": "302680",
        "code": "CZ",
        "name": "Czech Republic",
        "continent": "EU",
        "wikipedia_link": "https://en.wikipedia.org/wiki/Czech_Republic",
        "keywords": "Letiště České republiky, Czechia"
    },
    "region": {
        "id": "303538",
        "code": "CZ-OL",
        "local_code": "OL",
        "name": "Olomouc Region",
        "continent": "EU",
        "iso_country": "CZ",
        "wikipedia_link": "https://en.wikipedia.org/wiki/Olomouc_Region",
        "keywords": "Olomoucký kraj, Moravia"
    }
}