{
    "id": "535443",
    "ident": "MX-2286",
    "type": "balloonport",
    "name": "Aerostat Balloon Field",
    "latitude_deg": "19.69485",
    "longitude_deg": "-98.824725",
    "elevation_ft": "7539",
    "continent": "NA",
    "iso_country": "MX",
    "iso_region": "MX-MEX",
    "municipality": "San Martin de Las Piramides",
    "scheduled_service": "no",
    "icao_code": "",
    "iata_code": "",
    "gps_code": "",
    "local_code": "ZVFA",
    "home_link": "https://vuelaengloboaerostat.com/teotihuacan/",
    "wikipedia_link": "",
    "keywords": "",
    "country": {
        "id": "302747",
        "code": "MX",
        "name": "Mexico",
        "continent": "NA",
        "wikipedia_link": "https://en.wikipedia.org/wiki/Mexico",
        "keywords": "Aeropuertos de México, Mexican airports"
    },
    "region": {
        "id": "304804",
        "code": "MX-MEX",
        "local_code": "MEX",
        "name": "México (state)",
        "continent": "NA",
        "iso_country": "MX",
        "wikipedia_link": "https://en.wikipedia.org/wiki/State_of_Mexico",
        "keywords": "Airports in México (state)"
    }
}