{
    "id": "571915",
    "ident": "MX-2486",
    "type": "small_airport",
    "name": "Ignacio Valenzuela Lagarda Airport",
    "latitude_deg": "27.77379",
    "longitude_deg": "-108.5758",
    "elevation_ft": "5400",
    "continent": "NA",
    "iso_country": "MX",
    "iso_region": "MX-CHH",
    "municipality": "Chínipas",
    "scheduled_service": "no",
    "icao_code": "",
    "iata_code": "",
    "gps_code": "",
    "local_code": "",
    "home_link": "",
    "wikipedia_link": "",
    "keywords": "",
    "country": {
        "id": "302747",
        "code": "MX",
        "name": "Mexico",
        "continent": "NA",
        "wikipedia_link": "https://en.wikipedia.org/wiki/Mexico",
        "keywords": "Aeropuertos de México, Mexican airports"
    },
    "region": {
        "id": "304794",
        "code": "MX-CHH",
        "local_code": "CHH",
        "name": "Chihuahua",
        "continent": "NA",
        "iso_country": "MX",
        "wikipedia_link": "https://en.wikipedia.org/wiki/Chihuahua_(state)",
        "keywords": "Airports in Chihuahua"
    }
}