{
    "id": "349559",
    "ident": "PH-0440",
    "type": "closed",
    "name": "Lanuza (Carmen) Airport",
    "latitude_deg": "9.231363",
    "longitude_deg": "125.997923",
    "elevation_ft": "43",
    "continent": "AS",
    "iso_country": "PH",
    "iso_region": "PH-SUR",
    "municipality": "Carmen",
    "scheduled_service": "no",
    "icao_code": "",
    "iata_code": "",
    "gps_code": "",
    "local_code": "",
    "home_link": "",
    "wikipedia_link": "",
    "keywords": "",
    "country": {
        "id": "302656",
        "code": "PH",
        "name": "Philippines",
        "continent": "AS",
        "wikipedia_link": "https://en.wikipedia.org/wiki/Philippines",
        "keywords": "Mga alternatibong byahe mula sa Pilipinas"
    },
    "region": {
        "id": "305126",
        "code": "PH-SUR",
        "local_code": "SUR",
        "name": "Surigao del Sur Province",
        "continent": "AS",
        "iso_country": "PH",
        "wikipedia_link": "https://en.wikipedia.org/wiki/Surigao_del_Sur_Province",
        "keywords": "Airports in Surigao del Sur Province"
    }
}