{
    "id": "515942",
    "ident": "PL-0228",
    "type": "heliport",
    "name": "Kłodzko District Hospital Heliport",
    "latitude_deg": "50.45575",
    "longitude_deg": "16.66357",
    "elevation_ft": "974",
    "continent": "EU",
    "iso_country": "PL",
    "iso_region": "PL-DS",
    "municipality": "Kłodzko",
    "scheduled_service": "no",
    "gps_code": "",
    "iata_code": "",
    "local_code": "",
    "home_link": "",
    "wikipedia_link": "",
    "keywords": "",
    "country": {
        "id": "302710",
        "code": "PL",
        "name": "Poland",
        "continent": "EU",
        "wikipedia_link": "https://en.wikipedia.org/wiki/Poland",
        "keywords": "Lotniska Polski"
    },
    "region": {
        "id": "305144",
        "code": "PL-DS",
        "local_code": "DS",
        "name": "Lower Silesian Voivodeship",
        "continent": "EU",
        "iso_country": "PL",
        "wikipedia_link": "https://en.wikipedia.org/wiki/Lower_Silesian_Voivodeship",
        "keywords": "Dolnośląskie"
    }
}