{
    "id": "561186",
    "ident": "SS4B",
    "type": "heliport",
    "name": "Avenida Consolação 1601 Helipad",
    "latitude_deg": "-23.551548",
    "longitude_deg": "-46.655588",
    "elevation_ft": "2993",
    "continent": "SA",
    "iso_country": "BR",
    "iso_region": "BR-SP",
    "municipality": "São Paulo",
    "scheduled_service": "no",
    "icao_code": "",
    "iata_code": "",
    "gps_code": "SS4B",
    "local_code": "SP0864",
    "home_link": "",
    "wikipedia_link": "",
    "keywords": "",
    "runways": [
        {
            "id": "561187",
            "airport_ref": "561186",
            "airport_ident": "SS4B",
            "length_ft": "69",
            "width_ft": "69",
            "surface": "CON",
            "lighted": "1",
            "closed": "0",
            "le_ident": "04",
            "le_latitude_deg": "",
            "le_longitude_deg": "",
            "le_elevation_ft": "",
            "le_heading_degT": "",
            "le_displaced_threshold_ft": "",
            "he_ident": "19",
            "he_latitude_deg": "",
            "he_longitude_deg": "",
            "he_elevation_ft": "",
            "he_heading_degT": "",
            "he_displaced_threshold_ft": ""
        }
    ],
    "country": {
        "id": "302791",
        "code": "BR",
        "name": "Brazil",
        "continent": "SA",
        "wikipedia_link": "https://en.wikipedia.org/wiki/Brazil",
        "keywords": "Brasil, Brasilian, Aeroportos do Brasil"
    },
    "region": {
        "id": "303224",
        "code": "BR-SP",
        "local_code": "SP",
        "name": "São Paulo",
        "continent": "SA",
        "iso_country": "BR",
        "wikipedia_link": "https://en.wikipedia.org/wiki/S%C3%A3o_Paulo_(state)",
        "keywords": "Airports in São Paulo"
    }
}