{
    "id": "599112",
    "ident": "SS8Z",
    "type": "small_airport",
    "name": "Grupo Carreira Airport",
    "latitude_deg": "-17.24745",
    "longitude_deg": "-51.35928",
    "elevation_ft": "2819",
    "continent": "SA",
    "iso_country": "BR",
    "iso_region": "BR-GO",
    "municipality": "Caiapônia",
    "scheduled_service": "no",
    "icao_code": "",
    "iata_code": "",
    "gps_code": "SS8Z",
    "local_code": "GO0403",
    "home_link": "",
    "wikipedia_link": "",
    "keywords": "",
    "country": {
        "id": "302791",
        "code": "BR",
        "name": "Brazil",
        "continent": "SA",
        "wikipedia_link": "https://en.wikipedia.org/wiki/Brazil",
        "keywords": "Brasil, Brasilian, Aeroportos do Brasil"
    },
    "region": {
        "id": "303207",
        "code": "BR-GO",
        "local_code": "GO",
        "name": "Goiás",
        "continent": "SA",
        "iso_country": "BR",
        "wikipedia_link": "https://en.wikipedia.org/wiki/Goiás",
        "keywords": "Airports in Goiás"
    }
}