{
    "id": "602046",
    "ident": "SS9M",
    "type": "heliport",
    "name": "Minas Gerais State Court Helistop",
    "latitude_deg": "-19.944592",
    "longitude_deg": "-43.922273",
    "elevation_ft": "3402",
    "continent": "SA",
    "iso_country": "BR",
    "iso_region": "BR-MG",
    "municipality": "Belo Horizonte",
    "scheduled_service": "no",
    "icao_code": "",
    "iata_code": "",
    "gps_code": "SS9M",
    "local_code": "MG0639",
    "home_link": "",
    "wikipedia_link": "",
    "keywords": "TJMG",
    "country": {
        "id": "302791",
        "code": "BR",
        "name": "Brazil",
        "continent": "SA",
        "wikipedia_link": "https://en.wikipedia.org/wiki/Brazil",
        "keywords": "Brasil, Brasilian, Aeroportos do Brasil"
    },
    "region": {
        "id": "303209",
        "code": "BR-MG",
        "local_code": "MG",
        "name": "Minas Gerais",
        "continent": "SA",
        "iso_country": "BR",
        "wikipedia_link": "https://en.wikipedia.org/wiki/Minas_Gerais",
        "keywords": "Airports in Minas Gerais"
    }
}