{
    "id": "46269",
    "ident": "UA-0061",
    "type": "closed",
    "name": "Dalnik Airfield",
    "latitude_deg": "46.493108",
    "longitude_deg": "30.618859",
    "elevation_ft": "213",
    "continent": "EU",
    "iso_country": "UA",
    "iso_region": "UA-51",
    "municipality": "Odessa",
    "scheduled_service": "no",
    "icao_code": "",
    "iata_code": "",
    "gps_code": "",
    "local_code": "",
    "home_link": "",
    "wikipedia_link": "",
    "keywords": "Zastava Airfield, Аэродром Дальник, Аэродром Застава",
    "country": {
        "id": "302719",
        "code": "UA",
        "name": "Ukraine",
        "continent": "EU",
        "wikipedia_link": "https://en.wikipedia.org/wiki/Ukraine",
        "keywords": "Аеропорти України"
    },
    "region": {
        "id": "305997",
        "code": "UA-51",
        "local_code": "51",
        "name": "Odessa Oblast",
        "continent": "EU",
        "iso_country": "UA",
        "wikipedia_link": "https://en.wikipedia.org/wiki/Odessa_Oblast",
        "keywords": "Airports in Odessa Oblast"
    }
}