{
    "id": "349614",
    "ident": "US-12643",
    "type": "closed",
    "name": "Piney Point Airport",
    "latitude_deg": "38.14846",
    "longitude_deg": "-76.52218",
    "elevation_ft": "9",
    "continent": "NA",
    "iso_country": "US",
    "iso_region": "US-MD",
    "municipality": "Piney Point",
    "scheduled_service": "no",
    "icao_code": "",
    "iata_code": "",
    "gps_code": "",
    "local_code": "",
    "home_link": "",
    "wikipedia_link": "",
    "keywords": "MD96",
    "country": {
        "id": "302755",
        "code": "US",
        "name": "United States",
        "continent": "NA",
        "wikipedia_link": "https://en.wikipedia.org/wiki/United_States",
        "keywords": "American airports"
    },
    "region": {
        "id": "306096",
        "code": "US-MD",
        "local_code": "MD",
        "name": "Maryland",
        "continent": "NA",
        "iso_country": "US",
        "wikipedia_link": "https://en.wikipedia.org/wiki/Maryland",
        "keywords": "Airports in Maryland"
    }
}