{
    "id": "510744",
    "ident": "US-7882",
    "type": "small_airport",
    "name": "Hopkins Airport",
    "latitude_deg": "36.60025",
    "longitude_deg": "-90.25202",
    "elevation_ft": "311",
    "continent": "NA",
    "iso_country": "US",
    "iso_region": "US-MO",
    "municipality": "Qulin",
    "scheduled_service": "no",
    "icao_code": "",
    "iata_code": "",
    "gps_code": "",
    "local_code": "",
    "home_link": "",
    "wikipedia_link": "",
    "keywords": "",
    "country": {
        "id": "302755",
        "code": "US",
        "name": "United States",
        "continent": "NA",
        "wikipedia_link": "https://en.wikipedia.org/wiki/United_States",
        "keywords": "American airports"
    },
    "region": {
        "id": "306100",
        "code": "US-MO",
        "local_code": "MO",
        "name": "Missouri",
        "continent": "NA",
        "iso_country": "US",
        "wikipedia_link": "https://en.wikipedia.org/wiki/Missouri",
        "keywords": "Airports in Missouri"
    }
}