{
    "id": "331796",
    "ident": "WAME",
    "type": "small_airport",
    "name": "Buli Airport",
    "latitude_deg": "0.917144",
    "longitude_deg": "128.382116",
    "elevation_ft": "7",
    "continent": "AS",
    "iso_country": "ID",
    "iso_region": "ID-MU",
    "municipality": "Pekaulang",
    "scheduled_service": "yes",
    "gps_code": "WAEM",
    "iata_code": "PGQ",
    "local_code": "",
    "home_link": "",
    "wikipedia_link": "https://en.wikipedia.org/wiki/Buli_Airport",
    "keywords": "",
    "country": {
        "id": "302632",
        "code": "ID",
        "name": "Indonesia",
        "continent": "AS",
        "wikipedia_link": "https://en.wikipedia.org/wiki/Indonesia",
        "keywords": "Bandara di Indonesia"
    },
    "region": {
        "id": "304115",
        "code": "ID-MU",
        "local_code": "MU",
        "name": "Maluku Utara (North Maluku)",
        "continent": "AS",
        "iso_country": "ID",
        "wikipedia_link": "https://en.wikipedia.org/wiki/Maluku_Utara",
        "keywords": "Airports in Maluku Utara"
    }
}