{
    "id": "430064",
    "ident": "YCVN",
    "type": "heliport",
    "name": "FPSO Challis Venture Helipad",
    "latitude_deg": "-12.133333",
    "longitude_deg": "125.016667",
    "elevation_ft": "50",
    "continent": "OC",
    "iso_country": "AU",
    "iso_region": "AU-U-A",
    "municipality": "Timor Sea",
    "scheduled_service": "no",
    "gps_code": "YCVN",
    "iata_code": "",
    "local_code": "",
    "home_link": "https://web.archive.org/web/20160808181608/https://www.ihi.co.jp/offshore/challisventure_e.htm",
    "wikipedia_link": "",
    "keywords": "",
    "country": {
        "id": "302764",
        "code": "AU",
        "name": "Australia",
        "continent": "OC",
        "wikipedia_link": "https://en.wikipedia.org/wiki/Australia",
        "keywords": "Australian airports"
    },
    "region": {
        "id": "302974",
        "code": "AU-U-A",
        "local_code": "U-A",
        "name": "(unassigned)",
        "continent": "OC",
        "iso_country": "AU",
        "wikipedia_link": "",
        "keywords": "Airports in (unassigned)"
    }
}