{
    "id": "517039",
    "ident": "YE-0015",
    "type": "small_airport",
    "name": "Um Ghareb Airfield",
    "latitude_deg": "18.399411",
    "longitude_deg": "49.127599",
    "elevation_ft": "",
    "continent": "AS",
    "iso_country": "YE",
    "iso_region": "YE-HD",
    "municipality": "Um Ghareb",
    "scheduled_service": "no",
    "icao_code": "",
    "iata_code": "",
    "gps_code": "",
    "local_code": "",
    "home_link": "",
    "wikipedia_link": "",
    "keywords": "",
    "country": {
        "id": "302671",
        "code": "YE",
        "name": "Yemen",
        "continent": "AS",
        "wikipedia_link": "https://en.wikipedia.org/wiki/Yemen",
        "keywords": "مطارات اليمن"
    },
    "region": {
        "id": "306281",
        "code": "YE-HD",
        "local_code": "HD",
        "name": "Hadhramaut Governorate",
        "continent": "AS",
        "iso_country": "YE",
        "wikipedia_link": "https://en.wikipedia.org/wiki/Hadhramaut_Governorate",
        "keywords": "Airports in Hadhramaut Governorate"
    }
}