{
    "id": "518728",
    "ident": "ZA-0322",
    "type": "small_airport",
    "name": "Black Oystercatcher",
    "latitude_deg": "-34.631111",
    "longitude_deg": "19.8275",
    "elevation_ft": "45",
    "continent": "AF",
    "iso_country": "ZA",
    "iso_region": "ZA-U-A",
    "municipality": "Bredasdrop",
    "scheduled_service": "no",
    "gps_code": "",
    "iata_code": "",
    "local_code": "",
    "home_link": "",
    "wikipedia_link": "",
    "keywords": "",
    "country": {
        "id": "302610",
        "code": "ZA",
        "name": "South Africa",
        "continent": "AF",
        "wikipedia_link": "https://en.wikipedia.org/wiki/South_Africa",
        "keywords": "South African airports"
    },
    "region": {
        "id": "306303",
        "code": "ZA-U-A",
        "local_code": "U-A",
        "name": "(unassigned)",
        "continent": "AF",
        "iso_country": "ZA",
        "wikipedia_link": "",
        "keywords": "Airports in (unassigned)"
    }
}